LICENSE
README.md
setup.py
damedb/__init__.py
damedb.egg-info/PKG-INFO
damedb.egg-info/SOURCES.txt
damedb.egg-info/dependency_links.txt
damedb.egg-info/namespace_packages.txt
damedb.egg-info/not-zip-safe
damedb.egg-info/requires.txt
damedb.egg-info/top_level.txt
damedb/files/__init__.py
damedb/tests/__init__.py
damedb/tests/test_damedb_mongo.py
damedb/tests/test_damedb_mysql.py
damedb/tests/test_damedb_psql.py
damedb/tests/test_damedb_redis.py
damedb/tests/test_damedb_sqlite.py