Metadata-Version: 1.1
Name: damedb
Version: 0.0.5
Summary: Learning Databases in Python from tests by David Arroyo MEnéndez
Home-page: http://github.com/davidam/damedb
Author: David Arroyo Menéndez
Author-email: davidam@gmail.com
License: GPLv3
Keywords: python3,libraries,databases
Platform: UNKNOWN
Classifier: Programming Language :: Python :: 3
Classifier: License :: OSI Approved :: GNU General Public License v3 (GPLv3)
Classifier: Operating System :: OS Independent
